evaluation/Evaluations.py
evaluation/Program.py
evaluation/__init__.py
evaluation/predictions/__init__.py
evaluation/reference_data/__init__.py
treasureisland/.DS_Store
treasureisland/IdentifyGI.py
treasureisland/Parameters.py
treasureisland/Predictor.py
treasureisland/PreprocessData.py
treasureisland/__init__.py
treasureisland/treasureisland.py
treasureisland/__pycache__/IdentifyGI.cpython-312.pyc
treasureisland/__pycache__/Parameters.cpython-312.pyc
treasureisland/__pycache__/Predictor.cpython-312.pyc
treasureisland/__pycache__/PreprocessData.cpython-312.pyc
treasureisland/__pycache__/__init__.cpython-312.pyc
treasureisland/__pycache__/treasureisland.cpython-312.pyc
treasureisland/models/.DS_Store
treasureisland/models/__init__.py
treasureisland/models/doc2vec_upgrade_gensim
treasureisland/models/embedding_dbow_bacillota_mar2_var2
treasureisland/models/embedding_dbow_short_genomeid
treasureisland/models/embedding_model
treasureisland/models/embedding_v2_bacillota
treasureisland/models/embedding_v3
treasureisland/models/embedding_v4
treasureisland/models/svm_embedding_dbow_bacillota_mar2_var2_vector
treasureisland/models/svm_embedding_dbow_short_genomeid_vector
treasureisland/models/svm_embedding_model_vector
treasureisland/models/svm_embedding_v2_bacillota_vector_2
treasureisland/models/svm_embedding_v3
treasureisland/models/svm_embedding_v3_short_vector
treasureisland/models/svm_embedding_v4
treasureisland/models/svm_genome_centric
treasureisland/models/svm_upgrade_gensim_sklearn
treasureisland/models/svm_upgrade_gensim_sklearn_1.0
treasureisland/models/svm_v2_bacillota
treasureisland/models/__pycache__/__init__.cpython-312.pyc
treasureisland-1.1.5.dist-info/LICENSE.txt
treasureisland-1.1.5.dist-info/METADATA
treasureisland-1.1.5.dist-info/WHEEL
treasureisland-1.1.5.dist-info/entry_points.txt
treasureisland-1.1.5.dist-info/top_level.txt
treasureisland-1.1.5.dist-info/RECORD
