Metadata-Version: 2.1
Name: treasureisland
Version: 1.1.5
Summary: Prediction of Genomic Islands
Home-page: https://github.com/priyamayur/GenomicIslandPrediction
Author: Priyanka Banerjee
Author-email: banerjee.p1104@gmail.com
Classifier: Programming Language :: Python :: 3
Classifier: License :: OSI Approved :: MIT License
Classifier: Operating System :: OS Independent
Requires-Python: >=3.7
License-File: LICENSE.txt
Requires-Dist: gensim >=4.3.2
Requires-Dist: biopython >=1.79
Requires-Dist: scikit-learn >=1.4.0
Requires-Dist: pandas
Requires-Dist: openpyxl
Requires-Dist: importlib-resources
Requires-Dist: numpy >=1.26.3
Requires-Dist: tqdm
